whiteprints/__init__.py
whiteprints/console.py
whiteprints/copier_run.py
whiteprints/debug_info.py
whiteprints/environment.py
whiteprints/loc.py
whiteprints/package_metadata.py
whiteprints/py.typed
whiteprints/uvx_run.py
whiteprints/cli/__init__.py
whiteprints/cli/__main__.py
whiteprints/cli/entrypoint.py
whiteprints/cli/exception.py
whiteprints/cli/init.py
whiteprints/cli/init_interface.py
whiteprints/cli/logs.py
whiteprints/cli/command/__init__.py
whiteprints/cli/command/init.py
whiteprints-0.11.0.dist-info/METADATA
whiteprints-0.11.0.dist-info/WHEEL
whiteprints-0.11.0.dist-info/entry_points.txt
whiteprints-0.11.0.dist-info/licenses/LICENSES/GPL-3.0-or-later.txt
whiteprints-0.11.0.dist-info/RECORD
