Metadata-Version: 2.4
Name: whiteprints
Version: 0.11.0
Summary: A Copier-based cookiecutter for creating Python projects managed by uv.
Project-URL: changelog, https://github.com/whiteprints/whiteprints/releases
Project-URL: discussions, https://github.com/whiteprints/whiteprints/discussions
Project-URL: documentation, https://github.com/whiteprints/whiteprints
Project-URL: download, https://github.com/whiteprints/whiteprints/releases
Project-URL: homepage, https://github.com/whiteprints/whiteprints
Project-URL: integration, https://github.com/whiteprints/whiteprints/actions
Project-URL: issues, https://github.com/whiteprints/whiteprints/issues
Project-URL: pypi, https://pypi.org/project/whiteprints
Project-URL: repository, https://github.com/whiteprints/whiteprints
Author: Romain Brault
Maintainer: Romain Brault
License-Expression: GPL-3.0-or-later
License-File: LICENSES/GPL-3.0-or-later.txt
Keywords: Python
Classifier: Development Status :: 2 - Pre-Alpha
Classifier: Environment :: Console
Classifier: Framework :: Pytest
Classifier: Framework :: Sphinx
Classifier: Intended Audience :: Developers
Classifier: Natural Language :: English
Classifier: Operating System :: OS Independent
Classifier: Programming Language :: Python
Classifier: Programming Language :: Python :: 3 :: Only
Classifier: Programming Language :: Python :: 3.9
Classifier: Programming Language :: Python :: 3.10
Classifier: Programming Language :: Python :: 3.11
Classifier: Programming Language :: Python :: 3.12
Classifier: Programming Language :: Python :: 3.13
Classifier: Typing :: Typed
Requires-Python: <4.0,>=3.9
Requires-Dist: distro==1.9
Requires-Dist: importlib-metadata==8.5; python_full_version < '3.10'
Requires-Dist: python-dotenv==1.0.1
Requires-Dist: rich-click==1.8.5
Requires-Dist: typing-extensions==4.12.2; python_full_version < '3.12'
Requires-Dist: uv==0.5.17
